sanger_sequencing/__init__.py
sanger_sequencing/_version.py
sanger_sequencing/api.py
sanger_sequencing/config.py
sanger_sequencing/helpers.py
sanger_sequencing/analysis/__init__.py
sanger_sequencing/analysis/alignment.py
sanger_sequencing/analysis/sample.py
sanger_sequencing/analysis/summary.py
sanger_sequencing/clients/__init__.py
sanger_sequencing/clients/benchling.py
sanger_sequencing/clients/ice.py
sanger_sequencing/clients/labcollector.py
sanger_sequencing/clients/repository_client.py
sanger_sequencing/validation/__init__.py
sanger_sequencing/validation/plasmid.py
sanger_sequencing/validation/sample.py
sanger_sequencing/validation/template.py
sanger_sequencing/validation/schemata/__init__.py
sanger_sequencing/validation/schemata/template.json
sanger_sequencing-0.1.1.dist-info/METADATA
sanger_sequencing-0.1.1.dist-info/RECORD
sanger_sequencing-0.1.1.dist-info/WHEEL
sanger_sequencing-0.1.1.dist-info/top_level.txt
sanger_sequencing-0.1.1.dist-info/zip-safe
