Metadata-Version: 2.1
Name: sanger-sequencing
Version: 0.1.1
Summary: Semi-automated Sanger sequence analysis for transformation verification.
Home-page: https://github.com/biosustain/sanger-sequencing
Author: Novo Nordisk Foundation Center for Biosustainability, Technical University Denmark
Author-email: niso@biosustain.dtu.dk
Maintainer: Moritz E. Beber
Maintainer-email: morbeb@biosustain.dtu.dk
License: Apache Software License Version 2.0
Download-URL: https://pypi.org/project/sanger-sequencing/
Keywords: Sanger sequencing,automated analysis,mix2seq,plasmid verification
Platform: UNKNOWN
Classifier: Development Status :: 4 - Beta
Classifier: Intended Audience :: Developers
Classifier: Intended Audience :: Science/Research
Classifier: License :: OSI Approved :: Apache Software License
Classifier: Natural Language :: English
Classifier: Operating System :: POSIX
Classifier: Programming Language :: Python :: 3.6
Classifier: Programming Language :: Python :: 3.7
Classifier: Topic :: Scientific/Engineering :: Bio-Informatics
Requires-Python: >=3.6
Requires-Dist: depinfo
Requires-Dist: biopython
Requires-Dist: numpy
Requires-Dist: pandas
Requires-Dist: xlrd
Requires-Dist: requests
Requires-Dist: goodtables
Requires-Dist: importlib-resources
